pytrustplatform/__init__.py
pytrustplatform/ca_create.py
pytrustplatform/cert_get_data.py
pytrustplatform/cli_certificate_main.py
pytrustplatform/cli_manifest_main.py
pytrustplatform/cli_pytrust.py
pytrustplatform/compressed_cert_decoder.py
pytrustplatform/device_cert_builder.py
pytrustplatform/ecc_cert_builder.py
pytrustplatform/ecc_conversions.py
pytrustplatform/ecc_types.py
pytrustplatform/logfilters.py
pytrustplatform/logging.yaml
pytrustplatform/pytrust_errors.py
pytrustplatform/serialnumber.py
pytrustplatform/status_codes.py
pytrustplatform/verification_cert_builder.py
pytrustplatform/certs/template_device.csr
pytrustplatform/certs/ATECC608A-MAH1H/device.crt
pytrustplatform/certs/ATECC608A-MAH1H/signer_218B.crt
pytrustplatform/certs/ATECC608A-MAH4I/device_template.crt
pytrustplatform/certs/ATECC608A-MAH4I/signer_2C10.crt
pytrustplatform/certs/ATECC608B-TNGTLS/device_template.crt
pytrustplatform/certs/RootCA/ATECC Root CA 001.crt
pytrustplatform/certs/RootCA/Crypto Authentication Root CA 002.crt
pytrustplatform/manifest/__init__.py
pytrustplatform/manifest/data_provider.py
pytrustplatform/manifest/manifest.py
pytrustplatform/manifest/manifest_functions.py
pytrustplatform/manifest/mchp_manifest_signers/MCHP_manifest_signer_1_Jan2019_July2019.crt
pytrustplatform/manifest/mchp_manifest_signers/MCHP_manifest_signer_2_Aug2019_Aug2020.crt
pytrustplatform/manifest/mchp_manifest_signers/MCHP_manifest_signer_3_Aug-13-2020-Aug-13-2023.crt
pytrustplatform-1.1.4.18.dist-info/LICENSE.txt
pytrustplatform-1.1.4.18.dist-info/METADATA
pytrustplatform-1.1.4.18.dist-info/WHEEL
pytrustplatform-1.1.4.18.dist-info/entry_points.txt
pytrustplatform-1.1.4.18.dist-info/top_level.txt
pytrustplatform-1.1.4.18.dist-info/RECORD
