Metadata-Version: 2.1
Name: pytrustplatform
Version: 1.1.4.18
Summary: A collection of utilities for interacting with Microchip Trust Platform and Microchip CryptoAuthentication™ devices
Author-email: Microchip Technology <support@microchip.com>
License: MIT
Project-URL: Homepage, https://github.com/microchip-pic-avr-tools/pytrustplatform
Keywords: Microchip,AVR-IOT,PIC-IOT
Classifier: Development Status :: 5 - Production/Stable
Classifier: Intended Audience :: Developers
Classifier: Topic :: Software Development :: Embedded Systems
Classifier: Programming Language :: Python :: 3
Classifier: Programming Language :: Python :: 3.8
Classifier: Programming Language :: Python :: 3.9
Classifier: Programming Language :: Python :: 3.10
Classifier: Programming Language :: Python :: 3.11
Classifier: Operating System :: Microsoft :: Windows
Classifier: Operating System :: POSIX :: Linux
Classifier: Operating System :: MacOS
Classifier: License :: OSI Approved :: MIT License
Requires-Python: >=3.8
License-File: LICENSE.txt
Requires-Dist: cryptography
Requires-Dist: asn1crypto
Requires-Dist: pytz
Requires-Dist: pyyaml
Requires-Dist: appdirs
Requires-Dist: pyserial
Requires-Dist: python-jose[cryptography]
Requires-Dist: pykitcommander >=2.7
Requires-Dist: pyedbglib >=2.22
Provides-Extra: dev
Requires-Dist: pylint >=2.15 ; extra == 'dev'
Provides-Extra: doc
Requires-Dist: mock ; extra == 'doc'
Requires-Dist: sphinx ; extra == 'doc'
Provides-Extra: test
Requires-Dist: mock ; extra == 'test'
Requires-Dist: pytest ; extra == 'test'
